setup.py
apex_cli.egg-info/PKG-INFO
apex_cli.egg-info/SOURCES.txt
apex_cli.egg-info/dependency_links.txt
apex_cli.egg-info/entry_points.txt
apex_cli.egg-info/requires.txt
apex_cli.egg-info/top_level.txt
src/__init__.py
src/apex_cli.py
src/new/__init__.py
src/new/function.py
src/pack/__init__.py
src/pack/install.py
src/templates/function.json.tmpl
src/templates/python3.6/main.py.tmpl