Metadata-Version: 1.2
Name: apex-cli
Version: 0.0.4
Summary: Command-line interface of apex(serverless framework)
Home-page: https://github.com/finwhale/apex-cli
Author: finwhale
Author-email: waitingforqodot@gmail.com
License: UNKNOWN
Download-URL: https://github.com/finwhale/apex-cli/archive/master.zip
Platform: UNKNOWN
Requires-Python: >=3.6
